pydoc_quarto/__init__.py
pydoc_quarto/_modidx.py
pydoc_quarto/core.py
pydoc_quarto-0.0.12.dist-info/LICENSE
pydoc_quarto-0.0.12.dist-info/METADATA
pydoc_quarto-0.0.12.dist-info/WHEEL
pydoc_quarto-0.0.12.dist-info/entry_points.txt
pydoc_quarto-0.0.12.dist-info/top_level.txt
pydoc_quarto-0.0.12.dist-info/RECORD
