Metadata-Version: 2.1
Name: pydoc-quarto
Version: 0.0.12
Summary: Generate minimal reference API docs from a python library in the form of markdown files that can be rendered in Quarto.
Home-page: https://github.com/hamelsmu/pydoc_quarto
Author: hamelsmu
Author-email: hamel.husain@gmail.com
License: Apache Software License 2.0
Keywords: quarto python
Platform: UNKNOWN
Classifier: Development Status :: 4 - Beta
Classifier: Intended Audience :: Developers
Classifier: Natural Language :: English
Classifier: Programming Language :: Python :: 3.7
Classifier: Programming Language :: Python :: 3.8
Classifier: Programming Language :: Python :: 3.9
Classifier: Programming Language :: Python :: 3.10
Classifier: License :: OSI Approved :: Apache Software License
Requires-Python: >=3.7
License-File: LICENSE
Requires-Dist: fastcore (==1.5.28)
Provides-Extra: dev
Requires-Dist: requests (==2.28.2) ; extra == 'dev'
